[
  {
    "id": 1,
    "title": "المسجد الحرام",
    "type": "مسجد",
    "location": "مكة المكرمة",
    "date": "بناء أول مسجد في عام 638",
    "highlight": "يحتوي على الكعبة المشرفة",
    "importance": "أقدس موقع في الإسلام",
    "related_to": "إبراهيم عليه السلام"
  },
  {
    "id": 2,
    "title": "المسجد النبوي",
    "type": "مسجد",
    "location": "المدينة المنورة",
    "date": "622",
    "highlight": "ثاني أكبر مسجد في الإسلام",
    "importance": "ثاني أقدس موقع في الإسلام",
    "related_to": "النبي محمد ﷺ"
  },
  {
    "id": 3,
    "title": "المسجد الأقصى",
    "type": "مسجد",
    "location": "القدس",
    "date": "705",
    "highlight": "أولى القبلتين",
    "importance": "ثالث أقدس موقع في الإسلام",
    "related_to": "معراج النبي محمد ﷺ"
  },
  {
    "id": 4,
    "title": "غار حراء",
    "type": "غار",
    "location": "مكة المكرمة",
    "date": "610",
    "highlight": "نزول الوحي",
    "importance": "موقع نزول أول آية من القرآن",
    "related_to": "النبي محمد ﷺ"
  },
  {
    "id": 5,
    "title": "جبل عرفات",
    "type": "جبل",
    "location": "مكة المكرمة",
    "date": "عام حجة الوداع",
    "highlight": "موقف عرفة",
    "importance": "ركن أساسي في الحج",
    "related_to": "حجة الوداع"
  },
  {
    "id": 6,
    "title": "مقبرة البقيع",
    "type": "مقبرة",
    "location": "المدينة المنورة",
    "date": "القرن السابع الهجري",
    "highlight": "تقع بها قبور الصحابة والتابعين",
    "importance": "موقع تاريخي وروحي هام",
    "related_to": "أصحاب النبي ﷺ"
  },
  {
    "id": 7,
    "title": "ضريح الشيخ عبد القادر الجيلاني",
    "type": "ضريح",
    "location": "بغداد، العراق",
    "date": "القرن الخامس الهجري",
    "highlight": "من أبرز أولياء الله في الصوفية",
    "importance": "مكان تقديس وروحاني",
    "related_to": "الشيخ عبد القادر"
  },
  {
    "id": 8,
    "title": "مكتبة الأزهر",
    "type": "مكتبة",
    "location": "القاهرة، مصر",
    "date": "970",
    "highlight": "أحد أقدم المكتبات الإسلامية",
    "importance": "مركز علمي وديني هام",
    "related_to": "الأزهر الشريف"
  },
  {
    "id": 9,
    "title": "جامعة القرويين",
    "type": "جامعة",
    "location": "فاس، المغرب",
    "date": "859",
    "highlight": "أقدم جامعة في العالم",
    "importance": "منارة للتعليم الإسلامي",
    "related_to": "التراث الإسلامي"
  },
  {
    "id": 10,
    "title": "متحف الآثار الإسلامية",
    "type": "متحف",
    "location": "القاهرة، مصر",
    "date": "القرن العشرين",
    "highlight": "يضم كنوز الحضارة الإسلامية",
    "importance": "يحافظ على التراث الديني",
    "related_to": "التاريخ الإسلامي"
  },
  {
    "id": 11,
    "title": "مسجد قباء",
    "type": "مسجد",
    "location": "المدينة المنورة",
    "date": "622",
    "highlight": "أول مسجد بني في الإسلام",
    "importance": "موقع تاريخي بارز",
    "related_to": "النبي محمد ﷺ"
  },
  {
    "id": 12,
    "title": "مسجد قبة الصخرة",
    "type": "مسجد",
    "location": "القدس",
    "date": "691",
    "highlight": "معلم معماري فريد",
    "importance": "موقع مقدس وتاريخي",
    "related_to": "معراج النبي محمد ﷺ"
  },
  {
    "id": 13,
    "title": "غار ثور",
    "type": "غار",
    "location": "منطقة جبل ثور",
    "date": "تاريخ قديم",
    "highlight": "يرتبط بالوحي والذكر",
    "importance": "موقع للتأمل الروحي",
    "related_to": "الوحي"
  },
  {
    "id": 14,
    "title": "جبل النور",
    "type": "جبل",
    "location": "مكة المكرمة",
    "date": "تاريخ قديم",
    "highlight": "مرتبط بنزول الوحي",
    "importance": "مقدس لدى المسلمين",
    "related_to": "النبي محمد ﷺ"
  },
  {
    "id": 15,
    "title": "ضريح الإمام علي",
    "type": "ضريح",
    "location": "النجف، العراق",
    "date": "القرن الأول الهجري",
    "highlight": "ضريح الإمام علي بن أبي طالب",
    "importance": "موقع مقدس للمسلمين الشيعة",
    "related_to": "الإمام علي"
  },
  {
    "id": 16,
    "title": "ضريح الإمام الحسين",
    "type": "ضريح",
    "location": "كربلاء، العراق",
    "date": "القرن الأول الهجري",
    "highlight": "موقع معركة كربلاء",
    "importance": "أهمية روحية عظيمة",
    "related_to": "الإمام الحسين"
  },
  {
    "id": 17,
    "title": "ضريح الإمام جعفر الصادق",
    "type": "ضريح",
    "location": "سامراء، العراق",
    "date": "القرن التاسع الهجري",
    "highlight": "يحتضن ذكرى الإمام جعفر",
    "importance": "موقع مقدس للشيعة",
    "related_to": "الإمام جعفر"
  },
  {
    "id": 18,
    "title": "مسجد الملك فهد",
    "type": "مسجد",
    "location": "الرياض، السعودية",
    "date": "1982",
    "highlight": "معلم حضاري حديث",
    "importance": "رمز معاصر للوحدة الإسلامية",
    "related_to": "المبادئ الإسلامية"
  },
  {
    "id": 19,
    "title": "مسجد الحسن الثاني",
    "type": "مسجد",
    "location": "الدار البيضاء، المغرب",
    "date": "1993",
    "highlight": "من أكبر المساجد في المغرب",
    "importance": "يُعبر عن الحضارة الإسلامية في المغرب",
    "related_to": "الملك الحسن الثاني"
  },
  {
    "id": 20,
    "title": "ضريح الإمام الحسين",
    "type": "ضريح",
    "location": "كربلاء، العراق",
    "date": "القرن الأول الهجري",
    "highlight": "مرتبط بمأساة كربلاء",
    "importance": "أهم موقع روحي عند الشيعة",
    "related_to": "الإمام الحسين"
  },
  {
    "id": 21,
    "title": "متحف الحضارة الإسلامية",
    "type": "متحف",
    "location": "دبي، الإمارات",
    "date": "2016",
    "highlight": "يعرض تاريخ الحضارة الإسلامية",
    "importance": "مركز تثقيف وتراث",
    "related_to": "الحضارة الإسلامية"
  },
  {
    "id": 22,
    "title": "مسجد السلطان أحمد",
    "type": "مسجد",
    "location": "إسطنبول، تركيا",
    "date": "1609-1616",
    "highlight": "المعروف بــ'المسجد الأزرق'",
    "importance": "من روائع العمارة الإسلامية",
    "related_to": "الدولة العثمانية"
  },
  {
    "id": 23,
    "title": "الحمراء",
    "type": "قصر",
    "location": "غرناطة، إسبانيا",
    "date": "القرن الرابع عشر",
    "highlight": "أجمل معالم العمارة الإسلامية",
    "importance": "رمز الحضارة الإسلامية في الأندلس",
    "related_to": "الخلافة النصرية"
  },
  {
    "id": 24,
    "title": "جامع القيروان",
    "type": "مسجد",
    "location": "القيروان، تونس",
    "date": "670",
    "highlight": "أقدم مسجد في أفريقيا",
    "importance": "منارات الحضارة الإسلامية",
    "related_to": "الفتوحات الإسلامية"
  },
  {
    "id": 25,
    "title": "مسجد الجامع الكبير",
    "type": "مسجد",
    "location": "فاس، المغرب",
    "date": "القرن التاسع",
    "highlight": "جامع تاريخي عظيم",
    "importance": "مركز ديني وثقافي",
    "related_to": "التراث الإسلامي"
  },
  {
    "id": 26,
    "title": "مسجد ابن جزيل",
    "type": "مسجد",
    "location": "دمشق، سوريا",
    "date": "1150",
    "highlight": "مثال على العمارة الأيوبية",
    "importance": "ذو قيمة تاريخية",
    "related_to": "الثقافة الإسلامية"
  },
  {
    "id": 27,
    "title": "مسجد المغاربة",
    "type": "مسجد",
    "location": "فاس، المغرب",
    "date": "القرن الثالث عشر",
    "highlight": "معلم هام في فاس",
    "importance": "يعكس تاريخ المغرب الإسلامي",
    "related_to": "التراث المغربي"
  },
  {
    "id": 28,
    "title": "متحف القرم الإسلامي",
    "type": "متحف",
    "location": "الدار البيضاء، المغرب",
    "date": "2018",
    "highlight": "يعرض تاريخ الحضارة الإسلامية في البحر الأبيض المتوسط",
    "importance": "تثقيف وتراث متجدد",
    "related_to": "الحضارة الإسلامية"
  },
  {
    "id": 29,
    "title": "مكتبة الأندلس",
    "type": "مكتبة",
    "location": "قرطبة، إسبانيا",
    "date": "القرن العاشر",
    "highlight": "مركز للمعرفة والفنون",
    "importance": "أثر حضاري عظيم",
    "related_to": "الأندلس"
  },
  {
    "id": 30,
    "title": "جامعة الأزهر",
    "type": "جامعة",
    "location": "القاهرة، مصر",
    "date": "970",
    "highlight": "من أقدم الجامعات الإسلامية",
    "importance": "مركز للتعليم والفقه",
    "related_to": "الأزهر الشريف"
  },
  {
    "id": 31,
    "title": "مركز البحوث الإسلامية",
    "type": "مركز بحوث",
    "location": "دبي، الإمارات",
    "date": "2000",
    "highlight": "يدعم الأبحاث في التاريخ الإسلامي",
    "importance": "يساهم في النهضة الفكرية",
    "related_to": "الحضارة الإسلامية"
  },
  {
    "id": 32,
    "title": "مسجد ابن رشد",
    "type": "مسجد",
    "location": "قرطبة، إسبانيا",
    "date": "القرن الثاني عشر",
    "highlight": "مرتبط بالفيلسوف ابن رشد",
    "importance": "رمز للتعايش الثقافي",
    "related_to": "التراث الأندلسي"
  },
  {
    "id": 33,
    "title": "مسرح الحضارة الإسلامية",
    "type": "مسرح",
    "location": "القاهرة، مصر",
    "date": "القرن العشرين",
    "highlight": "يمثل التراث الإسلامي في الأداء الفني",
    "importance": "منبر فني وثقافي",
    "related_to": "الفنون الإسلامية"
  },
  {
    "id": 34,
    "title": "ضريح السيوف",
    "type": "ضريح",
    "location": "دمشق، سوريا",
    "date": "القرن الثالث عشر",
    "highlight": "ضريح شخصية دينية عظيمة",
    "importance": "مكان مقدس للصوفية",
    "related_to": "أولياء الله"
  },
  {
    "id": 35,
    "title": "مسجد أبو الحسن",
    "type": "مسجد",
    "location": "القصرين، تونس",
    "date": "القرن التاسع",
    "highlight": "من أقدم المساجد في تونس",
    "importance": "موقع تاريخي وروحي",
    "related_to": "التراث الإسلامي"
  },
  {
    "id": 36,
    "title": "مسجد ابن قيم",
    "type": "مسجد",
    "location": "دمشق، سوريا",
    "date": "القرن الثالث عشر",
    "highlight": "مرتبط بالفقيه ابن قيم الجوزية",
    "importance": "أثر ديني وأدبي",
    "related_to": "الإمام ابن قيم"
  },
  {
    "id": 37,
    "title": "ضريح الشافعي",
    "type": "ضريح",
    "location": "بغداد، العراق",
    "date": "القرن العاشر",
    "highlight": "يضم آثار الإمام الشافعي",
    "importance": "تاريخي وفكري",
    "related_to": "الإمام الشافعي"
  },
  {
    "id": 38,
    "title": "مسجد دار السلام",
    "type": "مسجد",
    "location": "بغداد، العراق",
    "date": "القرن العاشر",
    "highlight": "معلم إسلامي عظيم",
    "importance": "تاريخي وروحي",
    "related_to": "الإسلام"
  },
  {
    "id": 39,
    "title": "مكتبة الأندلس",
    "type": "مكتبة",
    "location": "غرناطة، إسبانيا",
    "date": "القرن الرابع عشر",
    "highlight": "مركز للعلوم والآداب",
    "importance": "أثر حضاري عظيم",
    "related_to": "الأندلس"
  },
  {
    "id": 40,
    "title": "جامع بني ثابت",
    "type": "مسجد",
    "location": "القيروان، تونس",
    "date": "القرن الثامن",
    "highlight": "من أقدم المساجد الإسلامية",
    "importance": "جزء من التراث الإسلامي",
    "related_to": "الفتوحات الإسلامية"
  },
  {
    "id": 41,
    "title": "متحف الفن الإسلامي",
    "type": "متحف",
    "location": "القاهرة، مصر",
    "date": "1990",
    "highlight": "يضم معروضات من الفنون الإسلامية",
    "importance": "مركز تعليمي وثقافي",
    "related_to": "الفن الإسلامي"
  },
  {
    "id": 42,
    "title": "ضريح الإمام أحمد بن حنبل",
    "type": "ضريح",
    "location": "بغداد، العراق",
    "date": "القرن العاشر",
    "highlight": "مكان تقديس للإمام أحمد",
    "importance": "روحي وتاريخي",
    "related_to": "الإمام أحمد بن حنبل"
  },
  {
    "id": 43,
    "title": "مسجد الأزهر الحديث",
    "type": "مسجد",
    "location": "القاهرة، مصر",
    "date": "2000",
    "highlight": "تصميم معاصر على الطراز الإسلامي",
    "importance": "تجسيد للإسلام المعاصر",
    "related_to": "الأزهر الشريف"
  },
  {
    "id": 44,
    "title": "قصر الخلافة",
    "type": "قصر",
    "location": "دمشق، سوريا",
    "date": "القرن الثامن",
    "highlight": "كان مقر الخلافة الإسلامية",
    "importance": "حاكم سياسي وتاريخي",
    "related_to": "الخلافة الإسلامية"
  },
  {
    "id": 45,
    "title": "مسجد الملك فهد",
    "type": "مسجد",
    "location": "الرياض، السعودية",
    "date": "1982",
    "highlight": "معلم حضاري حديث",
    "importance": "رمز للوحدة المعاصرة",
    "related_to": "الإسلام"
  },
  {
    "id": 46,
    "title": "ضريح الإمام جعفر الصادق",
    "type": "ضريح",
    "location": "سامراء، العراق",
    "date": "القرن التاسع",
    "highlight": "يحتضن أثر الإمام جعفر",
    "importance": "موقع مقدس للشيعة",
    "related_to": "الإمام جعفر الصادق"
  },
  {
    "id": 47,
    "title": "مسجد الفتح الإسلامي",
    "type": "مسجد",
    "location": "القاهرة، مصر",
    "date": "القرن العاشر",
    "highlight": "يشهد على فتوحات المسلمين",
    "importance": "تاريخي وروحي",
    "related_to": "الفتوحات الإسلامية"
  },
  {
    "id": 48,
    "title": "غار السيدة مريم",
    "type": "غار",
    "location": "جبال لبنان",
    "date": "تاريخ غير محدد",
    "highlight": "يرتبط بتقاليد دينية متعددة",
    "importance": "موقع روحي وتراثي",
    "related_to": "السيدة مريم"
  },
  {
    "id": 49,
    "title": "جبل سنان",
    "type": "جبل",
    "location": "تركيا",
    "date": "تاريخ قديم",
    "highlight": "مرتبط بالأساطير الدينية",
    "importance": "رمز للمعتقدات الشرقية",
    "related_to": "الديانات السماوية"
  },
  {
    "id": 50,
    "title": "ضريح الشيخ جذب",
    "type": "ضريح",
    "location": "الجزائر",
    "date": "القرن الخامس الهجري",
    "highlight": "ضريح أحد أعظم الأولياء",
    "importance": "مكان للتأمل والدعاء",
    "related_to": "الأولياء"
  },
  {
    "id": 51,
    "title": "معبد قبا",
    "type": "معبد",
    "location": "مصر القديمة",
    "date": "3000 قبل الميلاد",
    "highlight": "أقدم معبد ديني",
    "importance": "أساس المعتقدات القديمة",
    "related_to": "الحضارة المصرية القديمة"
  },
  {
    "id": 52,
    "title": "مسجد أحمد بن حنبل",
    "type": "مسجد",
    "location": "القاهرة",
    "date": "القرن الثالث الهجري",
    "highlight": "مرتبط بالإمام أحمد",
    "importance": "تجسيد للفقه الإسلامي",
    "related_to": "الإمام أحمد بن حنبل"
  },
  {
    "id": 53,
    "title": "جامع الفتح في دمشق",
    "type": "مسجد",
    "location": "دمشق",
    "date": "القرن الرابع الهجري",
    "highlight": "أحد أبرز المساجد في الشام",
    "importance": "رمز تاريخي إسلامي",
    "related_to": "الفتوحات الإسلامية"
  },
  {
    "id": 54,
    "title": "مكتبة البصرة الإسلامية",
    "type": "مكتبة",
    "location": "البصرة، العراق",
    "date": "القرن الأول الهجري",
    "highlight": "مركز للعلوم الإسلامية",
    "importance": "منارة تعليم ديني عريقة",
    "related_to": "العلوم الإسلامية"
  },
  {
    "id": 55,
    "title": "متحف التراث الإسلامي",
    "type": "متحف",
    "location": "بيروت، لبنان",
    "date": "القرن العشرين",
    "highlight": "يضم معروضات أثرية دينية",
    "importance": "يحافظ على التراث الإسلامي",
    "related_to": "الحضارة الإسلامية"
  },
  {
    "id": 56,
    "title": "مسجد علي بن أبي طالب",
    "type": "مسجد",
    "location": "كربلاء، العراق",
    "date": "القرن الأول الهجري",
    "highlight": "مرتبط بالإمام علي بن أبي طالب",
    "importance": "موقع مقدس للشيعة",
    "related_to": "الإمام علي"
  },
  {
    "id": 57,
    "title": "ضريح زين العابدين",
    "type": "ضريح",
    "location": "كربلاء، العراق",
    "date": "القرن الأول الهجري",
    "highlight": "محل تقديس روحي",
    "importance": "ذو قيمة خاصة لدى الشيعة",
    "related_to": "زين العابدين"
  },
  {
    "id": 58,
    "title": "مسجد الإمام الحسن الثاني",
    "type": "مسجد",
    "location": "الدار البيضاء، المغرب",
    "date": "1993",
    "highlight": "من أكبر المساجد في المغرب",
    "importance": "رمز للحضارة المغربية",
    "related_to": "الملك الحسن الثاني"
  },
  {
    "id": 59,
    "title": "جامع الثقافة الإسلامية",
    "type": "مسجد",
    "location": "دمشق، سوريا",
    "date": "القرن الخامس الهجري",
    "highlight": "يضم مرافق تعليمية وثقافية",
    "importance": "منبر للمعرفة الدينية",
    "related_to": "الحضارة الإسلامية"
  },
  {
    "id": 60,
    "title": "متحف الآثار الدينية",
    "type": "متحف",
    "location": "القاهرة، مصر",
    "date": "2010",
    "highlight": "يستعرض تاريخ المعتقدات الدينية",
    "importance": "يحافظ على التراث الديني",
    "related_to": "المعتقدات القديمة"
  },
  {
    "id": 61,
    "title": "مسجد الرضا",
    "type": "مسجد",
    "location": "المدينة المنورة، السعودية",
    "date": "القرن الأول الهجري",
    "highlight": "مرتبط بمواقعه الروحية",
    "importance": "رمز للتسامح الديني",
    "related_to": "النبي محمد ﷺ"
  },
  {
    "id": 62,
    "title": "ضريح السلطان الأكبر",
    "type": "ضريح",
    "location": "القاهرة، مصر",
    "date": "القرن الثالث الهجري",
    "highlight": "يحتضن آثار سلطان بارز",
    "importance": "موقع تاريخي هام",
    "related_to": "السلطان الأكبر"
  },
  {
    "id": 63,
    "title": "مسجد السلام العالمي",
    "type": "مسجد",
    "location": "دبي، الإمارات",
    "date": "2015",
    "highlight": "يحتضن فعاليات السلام",
    "importance": "جهة للتعارف الديني العالمي",
    "related_to": "رسالة السلام"
  },
  {
    "id": 64,
    "title": "جامعة الحضارة الإسلامية",
    "type": "جامعة",
    "location": "الرياض، السعودية",
    "date": "2010",
    "highlight": "تأصيل للعلوم الإسلامية",
    "importance": "منبر للتعليم والإصلاح",
    "related_to": "التراث الإسلامي"
  },
  {
    "id": 65,
    "title": "مكتبة التراث الإسلامي",
    "type": "مكتبة",
    "location": "الدار البيضاء، المغرب",
    "date": "القرن العشرين",
    "highlight": "تحفة تراثية للمخطوطات النادرة",
    "importance": "يحافظ على المخطوطات الثمينة",
    "related_to": "الحضارة الإسلامية"
  },
  {
    "id": 66,
    "title": "مسجد دار العلم",
    "type": "مسجد",
    "location": "دمشق، سوريا",
    "date": "القرن الخامس الهجري",
    "highlight": "محراب للمعرفة الإسلامية",
    "importance": "منارة للعلم والدين",
    "related_to": "التعليم الإسلامي"
  },
  {
    "id": 67,
    "title": "مركز الدراسات الإسلامية",
    "type": "مركز بحوث",
    "location": "بيروت، لبنان",
    "date": "2012",
    "highlight": "يقدم بحوثاً متقدمة في الفكر الإسلامي",
    "importance": "يساهم في النهضة الفكرية",
    "related_to": "الدراسات الإسلامية"
  },
  {
    "id": 68,
    "title": "مسجد دار الحكمة",
    "type": "مسجد",
    "location": "القاهرة، مصر",
    "date": "القرن الخامس الهجري",
    "highlight": "يرمز للمعرفة والفهم",
    "importance": "محطة للفكر الإسلامي",
    "related_to": "الحضارة الإسلامية"
  },
  {
    "id": 69,
    "title": "متحف تاريخ الإسلام",
    "type": "متحف",
    "location": "المدينة المنورة، السعودية",
    "date": "2018",
    "highlight": "يروي قصة النشأة الإسلامية",
    "importance": "يحافظ على التاريخ الإسلامي",
    "related_to": "السيرة النبوية"
  },
  {
    "id": 70,
    "title": "مسجد دار الفتوح",
    "type": "مسجد",
    "location": "القاهرة، مصر",
    "date": "القرن الرابع الهجري",
    "highlight": "يروي معارك الفتح الإسلامي",
    "importance": "رمز للتاريخ الإسلامي",
    "related_to": "الفتوحات الإسلامية"
  },
  {
    "id": 71,
    "title": "ضريح قادة الأمة",
    "type": "ضريح",
    "location": "بغداد، العراق",
    "date": "القرن العاشر",
    "highlight": "يحتضن ذكرى قادة الإسلام",
    "importance": "موقع للتقديس والذكر",
    "related_to": "القادة الدينيين"
  },
  {
    "id": 72,
    "title": "مسجد دار الندى",
    "type": "مسجد",
    "location": "دمشق، سوريا",
    "date": "القرن الخامس الهجري",
    "highlight": "يتميز بجمال زخارفه",
    "importance": "رمز للتأمل الروحي",
    "related_to": "الفنون الإسلامية"
  },
  {
    "id": 73,
    "title": "مركز الوعظ الإسلامي",
    "type": "مركز",
    "location": "القاهرة، مصر",
    "date": "القرن العشرين",
    "highlight": "ينشر خطباً ودروساً دينية",
    "importance": "منبر للتوعية الدينية",
    "related_to": "التعليم الديني"
  },
  {
    "id": 74,
    "title": "مسجد دار البركة",
    "type": "مسجد",
    "location": "فاس، المغرب",
    "date": "القرن الخامس الهجري",
    "highlight": "يشتهر بمعماره الفريد",
    "importance": "رمز للحضارة المغربية",
    "related_to": "التراث الإسلامي"
  },
  {
    "id": 75,
    "title": "ضريح الشيخ زايد",
    "type": "ضريح",
    "location": "أبوظبي، الإمارات",
    "date": "القرن العشرين",
    "highlight": "يكرم شخصية قيادية بارزة",
    "importance": "رمز للوحدة الوطنية والدين",
    "related_to": "القيادات الإسلامية"
  },
  {
    "id": 76,
    "title": "مسجد دار الوحدة",
    "type": "مسجد",
    "location": "القاهرة، مصر",
    "date": "القرن السادس الهجري",
    "highlight": "يشهد على وحدة الأمة الإسلامية",
    "importance": "رمز للتآزر والوحدة",
    "related_to": "الإسلام"
  },
  {
    "id": 77,
    "title": "مركز الثقافة الإسلامية",
    "type": "مركز",
    "location": "الدار البيضاء، المغرب",
    "date": "2010",
    "highlight": "يعرض الفنون والتراث الإسلامي",
    "importance": "منبر للثقافة الدينية",
    "related_to": "الحضارة الإسلامية"
  },
  {
    "id": 78,
    "title": "متحف الإسراء والمعراج",
    "type": "متحف",
    "location": "المدينة المنورة، السعودية",
    "date": "2017",
    "highlight": "يروي قصة الإسراء والمعراج",
    "importance": "موقع تاريخي ديني",
    "related_to": "النبي محمد ﷺ"
  },
  {
    "id": 79,
    "title": "مسجد دار الرحمن",
    "type": "مسجد",
    "location": "دمشق، سوريا",
    "date": "القرن الرابع الهجري",
    "highlight": "يرمز إلى رحمة الله",
    "importance": "مركز للتأمل الروحي",
    "related_to": "الإسلام"
  },
  {
    "id": 80,
    "title": "ضريح السلطان عبد المجيد",
    "type": "ضريح",
    "location": "القاهرة، مصر",
    "date": "القرن السادس الهجري",
    "highlight": "يحمل أثر الخلفاء العباسيين",
    "importance": "موقع تاريخي مقدس",
    "related_to": "الخلفاء"
  },
  {
    "id": 81,
    "title": "مسجد دار الوفاء",
    "type": "مسجد",
    "location": "الدار البيضاء، المغرب",
    "date": "القرن السادس الهجري",
    "highlight": "يرمز للتفاني والإخلاص",
    "importance": "من المعالم الدينية البارزة",
    "related_to": "التاريخ الإسلامي"
  },
  {
    "id": 82,
    "title": "مركز الدراسات والبحوث الدينية",
    "type": "مركز بحوث",
    "location": "الرياض، السعودية",
    "date": "2015",
    "highlight": "يدعم البحث العلمي في الشريعة",
    "importance": "يساهم في تطوير الفقه الإسلامي",
    "related_to": "الدراسات الإسلامية"
  },
  {
    "id": 83,
    "title": "مسجد دار الإخلاص",
    "type": "مسجد",
    "location": "دمشق، سوريا",
    "date": "القرن السادس الهجري",
    "highlight": "يركز على صفاء القلب",
    "importance": "رمز للتقوى والإخلاص",
    "related_to": "القيم الإسلامية"
  },
  {
    "id": 84,
    "title": "مكتبة التراث والنيل",
    "type": "مكتبة",
    "location": "الأسكندرية، مصر",
    "date": "القرن العشرين",
    "highlight": "تضم مخطوطات أثرية نادرة",
    "importance": "يحافظ على التراث الإسلامي والقبطي",
    "related_to": "التراث"
  },
  {
    "id": 85,
    "title": "مسجد دار الدعوة",
    "type": "مسجد",
    "location": "دمشق، سوريا",
    "date": "القرن الخامس الهجري",
    "highlight": "يجمع بين الروحانية والتعليم",
    "importance": "منبر للدعوة إلى الإسلام",
    "related_to": "الدعوة الإسلامية"
  },
  {
    "id": 86,
    "title": "مركز الأبحاث الإسلامية التطبيقية",
    "type": "مركز بحوث",
    "location": "القاهرة، مصر",
    "date": "2012",
    "highlight": "يطبق الأفكار الإسلامية في الواقع",
    "importance": "يساهم في تطوير الابتكار الديني",
    "related_to": "الحضارة الإسلامية"
  },
  {
    "id": 87,
    "title": "مسجد دار الوفاق",
    "type": "مسجد",
    "location": "المدينة المنورة، السعودية",
    "date": "القرن الأول الهجري",
    "highlight": "يرمز إلى التآلف والوحدة",
    "importance": "موقع روحي وتاريخي",
    "related_to": "النبي محمد ﷺ"
  },
  {
    "id": 88,
    "title": "ضريح ولي الدين",
    "type": "ضريح",
    "location": "بغداد، العراق",
    "date": "القرن الثالث الهجري",
    "highlight": "ضريح لأحد الفقهاء العظماء",
    "importance": "مرجع روحي ودراسي",
    "related_to": "الفقه الإسلامي"
  },
  {
    "id": 89,
    "title": "مسجد دار العز",
    "type": "مسجد",
    "location": "دمشق، سوريا",
    "date": "القرن الخامس الهجري",
    "highlight": "متميز بزخارفه الرائعة",
    "importance": "منارة روحية",
    "related_to": "الإسلام"
  },
  {
    "id": 90,
    "title": "جامعة العلوم الإسلامية",
    "type": "جامعة",
    "location": "القاهرة، مصر",
    "date": "2010",
    "highlight": "تخريج كوادر دينية عالية",
    "importance": "منبر للتعليم الإسلامي المتقدم",
    "related_to": "الدراسات الإسلامية"
  },
  {
    "id": 91,
    "title": "متحف الحضارة الإسلامية والتراث",
    "type": "متحف",
    "location": "الدار البيضاء، المغرب",
    "date": "2018",
    "highlight": "عرض لحضارة الإسلام عبر العصور",
    "importance": "مركز ثقافي وتراثي",
    "related_to": "التراث الإسلامي"
  },
  {
    "id": 92,
    "title": "مسجد دار الإحسان",
    "type": "مسجد",
    "location": "القاهرة، مصر",
    "date": "القرن السادس الهجري",
    "highlight": "يرى فيه المسلمون رمزاً للإحسان",
    "importance": "منارة للخير والبركة",
    "related_to": "القيم الإسلامية"
  },
  {
    "id": 93,
    "title": "مركز الحوار الإسلامي",
    "type": "مركز",
    "location": "القاهرة، مصر",
    "date": "2016",
    "highlight": "ملتقى للحوار بين الثقافات",
    "importance": "يدعم التعايش السلمي",
    "related_to": "القيم الإسلامية"
  },
  {
    "id": 94,
    "title": "مسجد دار الهدى",
    "type": "مسجد",
    "location": "المدينة المنورة، السعودية",
    "date": "القرن الأول الهجري",
    "highlight": "يروي قصة الهداية",
    "importance": "موقع مقدس",
    "related_to": "النبي محمد ﷺ"
  },
  {
    "id": 95,
    "title": "ضريح الصحابة",
    "type": "مقبرة/ضريح",
    "location": "المدينة المنورة، السعودية",
    "date": "القرن الأول الهجري",
    "highlight": "يضم قبور عدد من الصحابة",
    "importance": "موقع تاريخي وروحي",
    "related_to": "أصحاب النبي ﷺ"
  },
  {
    "id": 96,
    "title": "مسجد دار النور",
    "type": "مسجد",
    "location": "دمشق، سوريا",
    "date": "القرن الخامس الهجري",
    "highlight": "محاط بزخارف مبهرة",
    "importance": "رمز للنور والهداية",
    "related_to": "الإسلام"
  },
  {
    "id": 97,
    "title": "جامعة دار الحكمة",
    "type": "جامعة",
    "location": "الدار البيضاء، المغرب",
    "date": "2012",
    "highlight": "تعليم متعدد التخصصات الدينية",
    "importance": "منبر للنهوض العلمي",
    "related_to": "الحضارة الإسلامية"
  },
  {
    "id": 98,
    "title": "متحف الآثار الإسلامية الشرقية",
    "type": "متحف",
    "location": "بغداد، العراق",
    "date": "2015",
    "highlight": "يعرض كنوز الفنون الإسلامية",
    "importance": "مركز ثقافي وتراثي",
    "related_to": "التراث الإسلامي"
  },
  {
    "id": 99,
    "title": "مسجد دار البرهان",
    "type": "مسجد",
    "location": "القاهرة، مصر",
    "date": "القرن السادس الهجري",
    "highlight": "يروي قصة الإيمان والتقوى",
    "importance": "موقع روحي هام",
    "related_to": "الإسلام"
  },
  {
    "id": 100,
    "title": "مركز التوعية الإسلامية",
    "type": "مركز",
    "location": "الرياض، السعودية",
    "date": "2018",
    "highlight": "يقدم برامج تثقيفية وتوعوية",
    "importance": "يدعم نشر قيم الإسلام",
    "related_to": "الدعوة الإسلامية"
  }
]
